d_mixins/__init__.py
d_mixins/admin.py
d_mixins/apps.py
d_mixins/models.py
d_mixins/tests.py
d_mixins/views.py
d_mixins/migrations/__init__.py
d_mixins/templates/d_mixins/link_invalid.html
d_mixins/templates/d_mixins/public_link_expired.html
d_mixins/templates/d_mixins/public_link_invalid.html
d_mixins/templates/d_mixins/public_response_submitted.html
d_mixins/templates/d_mixins/public_response_success.html
d_mixins/templates/d_mixins/response_expired.html
d_mixins/templates/d_mixins/response_submitted.html
d_mixins/templates/d_mixins/response_success.html
d_mixins/templates/d_mixins/unauthorized_user.html
django_mixins_glib-0.0.1.1.dist-info/LICENSE
django_mixins_glib-0.0.1.1.dist-info/METADATA
django_mixins_glib-0.0.1.1.dist-info/WHEEL
django_mixins_glib-0.0.1.1.dist-info/top_level.txt
django_mixins_glib-0.0.1.1.dist-info/RECORD
